[{"domain": ".instagram.com", "expiry": 1783350855, "httpOnly": false, "name": "csrftoken", "path": "/", "sameSite": "Lax", "secure": true, "value": "aKH2x_m_gTA1oANcGFg_43"}, {"domain": ".instagram.com", "httpOnly": true, "name": "datr", "path": "/", "sameSite": "None", "secure": true, "value": "QQ41aJNNxEXR2hc2Iq_c9iKL"}, {"domain": ".instagram.com", "httpOnly": true, "name": "ig_did", "path": "/", "sameSite": "None", "secure": true, "value": "45DF723E-86CE-4407-A57C-76EB3402D1E8"}, {"domain": ".instagram.com", "httpOnly": true, "name": "ps_n", "path": "/", "sameSite": "None", "secure": true, "value": "1"}, {"domain": ".instagram.com", "expiry": 1749395651, "httpOnly": false, "name": "wd", "path": "/", "sameSite": "Lax", "secure": true, "value": "1350x621"}, {"domain": ".instagram.com", "expiry": 1756566855, "httpOnly": false, "name": "ds_user_id", "path": "/", "sameSite": "None", "secure": true, "value": "74916320994"}, {"domain": ".instagram.com", "httpOnly": true, "name": "ps_l", "path": "/", "sameSite": "Lax", "secure": true, "value": "1"}, {"domain": ".instagram.com", "expiry": 1780326855, "httpOnly": true, "name": "sessionid", "path": "/", "sameSite": "Lax", "secure": true, "value": "74916320994%3A5PHa5MAdhjrKfH%3A8%3AAYcQD0rY1foqcDKguD1hpAeWi7rH3fX29EkqipJlFg"}, {"domain": ".instagram.com", "httpOnly": false, "name": "mid", "path": "/", "sameSite": "Lax", "secure": true, "value": "aDUOQQALAAEGj883fbpHlfb50LJ5"}, {"domain": ".instagram.com", "httpOnly": true, "name": "rur", "path": "/", "sameSite": "Lax", "secure": true, "value": "\"NCG\\05474916320994\\0541780326855:01feb44e98296c0f305014300677bcf1a0f00f7d00ffb8d16c83acfe7cc31f400e86d817\""}, {"domain": ".instagram.com", "httpOnly": false, "name": "ig_nrcb", "path": "/", "sameSite": "Lax", "secure": true, "value": "1"}]