[
  {
    "domain": ".instagram.com",
    "expiry": 1781723839,
    "httpOnly": true,
    "name": "ps_n",
    "path": "/",
    "sameSite": "None",
    "secure": true,
    "value": "1"
  },
  {
    "domain": ".instagram.com",
    "expiry": 1781723839,
    "httpOnly": true,
    "name": "ps_l",
    "path": "/",
    "sameSite": "Lax",
    "secure": true,
    "value": "1"
  },
  {
    "domain": ".instagram.com",
    "expiry": 1747803885,
    "httpOnly": false,
    "name": "wd",
    "path": "/",
    "sameSite": "Lax",
    "secure": true,
    "value": "1264x705"
  },
  {
    "domain": ".instagram.com",
    "expiry": 1754975087,
    "httpOnly": false,
    "name": "ds_user_id",
    "path": "/",
    "sameSite": "None",
    "secure": true,
    "value": "60046643227"
  },
  {
    "domain": ".instagram.com",
    "expiry": 1778735087,
    "httpOnly": true,
    "name": "sessionid",
    "path": "/",
    "sameSite": "Lax",
    "secure": true,
    "value": "60046643227%3ADqa0j2vQ9dgPMt%3A20%3AAYfmVvSZ6Fa7nHdbdBsexUtR7-GrmnOIuXBE1b8ZHg"
  },
  {
    "domain": ".instagram.com",
    "expiry": 1781723830,
    "httpOnly": false,
    "name": "mid",
    "path": "/",
    "sameSite": "Lax",
    "secure": true,
    "value": "aCOatgALAAGtDg0s2Dl4ZuU2-H9Q"
  },
  {
    "domain": ".instagram.com",
    "httpOnly": true,
    "name": "rur",
    "path": "/",
    "sameSite": "Lax",
    "secure": true,
    "value": "\"NCG\\05460046643227\\0541778735087:01f756eebd4121a6b9b371c35addf62ef7486431355c0e398e266a4cafce74646ed50f3e\""
  },
  {
    "domain": ".instagram.com",
    "expiry": 1778699830,
    "httpOnly": false,
    "name": "ig_nrcb",
    "path": "/",
    "sameSite": "Lax",
    "secure": true,
    "value": "1"
  },
  {
    "domain": ".instagram.com",
    "expiry": 1778699828,
    "httpOnly": true,
    "name": "ig_did",
    "path": "/",
    "sameSite": "None",
    "secure": true,
    "value": "32BFE7E1-874C-4064-A539-51925639C584"
  },
  {
    "domain": ".instagram.com",
    "expiry": 1781723828,
    "httpOnly": true,
    "name": "datr",
    "path": "/",
    "sameSite": "None",
    "secure": true,
    "value": "tZojaGzssbKAJTyrEOeRQhXV"
  },
  {
    "domain": ".instagram.com",
    "expiry": 1781759087,
    "httpOnly": false,
    "name": "csrftoken",
    "path": "/",
    "sameSite": "Lax",
    "secure": true,
    "value": "Ti1E1qZdS9QQZUCTE_Hp9s"
  }
]